web/__init__.py
web/dao.py
web/database.py
web/dto.py
web/exceptions.py
web/middlewares.py
web/mongo_database.py
web/pg_database.py
web/unit.py
personal_web_utility-0.0.28.dist-info/METADATA
personal_web_utility-0.0.28.dist-info/WHEEL
personal_web_utility-0.0.28.dist-info/RECORD
