Metadata-Version: 2.3
Name: personal-web-utility
Version: 0.0.28
Summary: 
Author: mmacuka
Author-email: mihaelmacuka2@gmail.com
Requires-Python: >=3.11,<4.0
Classifier: Programming Language :: Python :: 3
Classifier: Programming Language :: Python :: 3.11
Classifier: Programming Language :: Python :: 3.12
Classifier: Programming Language :: Python :: 3.13
Requires-Dist: fastapi (>=0.109.1,<0.110.0)
Requires-Dist: psycopg2-binary (>=2.9.10,<3.0.0)
Requires-Dist: pymongo (>=4.13.2,<5.0.0)
Requires-Dist: uvicorn (>=0.23.2,<0.24.0)
